query_optimizer/__init__.py
query_optimizer/api.py
query_optimizer/adapters/__init__.py
query_optimizer/adapters/mysql.py
query_optimizer/adapters/postgres.py
query_optimizer/adapters/sqlite.py
query_optimizer/cli/__init__.py
query_optimizer/cli/main.py
query_optimizer/core/__init__.py
query_optimizer/core/analyzer.py
query_optimizer/core/models.py
query_optimizer/core/optimizer.py
query_optimizer-0.1.2.dist-info/licenses/LICENSE
query_optimizer-0.1.2.dist-info/METADATA
query_optimizer-0.1.2.dist-info/WHEEL
query_optimizer-0.1.2.dist-info/entry_points.txt
query_optimizer-0.1.2.dist-info/top_level.txt
query_optimizer-0.1.2.dist-info/RECORD
