Metadata-Version: 2.4
Name: query-optimizer
Version: 0.1.2
Summary: Universal SQL query optimizer to analyze, optimize, and monitor slow queries.
Home-page: https://github.com/makroumi/query-optimizer
Author: El Mehdi Makroumi
Author-email: Mehdi Makroumi <elmehdi.makroumi@gmail.com>
License: MIT
Project-URL: Homepage, https://github.com/makroumi/query-optimizer
Project-URL: Issues, https://github.com/makroumi/query-optimizer/issues
Keywords: sql,optimization,database,performance,postgres,mysql,monitoring
Classifier: Development Status :: 4 - Beta
Classifier: Intended Audience :: Developers
Classifier: Topic :: Database
Classifier: Topic :: Software Development :: Quality Assurance
Classifier: License :: OSI Approved :: MIT License
Classifier: Programming Language :: Python :: 3.8
Classifier: Programming Language :: Python :: 3.9
Classifier: Programming Language :: Python :: 3.10
Classifier: Programming Language :: Python :: 3.11
Classifier: Programming Language :: Python :: 3.12
Requires-Python: >=3.8
License-File: LICENSE
Requires-Dist: click>=8.1.0
Requires-Dist: psycopg2-binary>=2.9.0
Requires-Dist: mysql-connector-python>=8.0.0
Requires-Dist: sqlparse>=0.4.0
Requires-Dist: rich>=13.0.0
Requires-Dist: python-dotenv>=0.20.0
Provides-Extra: test
Requires-Dist: pytest>=7.0.0; extra == "test"
Requires-Dist: pytest-cov>=4.0.0; extra == "test"
Dynamic: author
Dynamic: home-page
Dynamic: license-file
Dynamic: requires-python
